sopel_stocks/__init__.py
sopel_stocks/plugin.py
sopel_stocks/providers/__init__.py
sopel_stocks/providers/alphavantage.py
sopel_stocks/providers/finnhub.py
sopel_stocks/providers/iexcloud.py
sopel_stocks-2.0.2.dist-info/licenses/LICENSE
sopel_stocks-2.0.2.dist-info/METADATA
sopel_stocks-2.0.2.dist-info/WHEEL
sopel_stocks-2.0.2.dist-info/entry_points.txt
sopel_stocks-2.0.2.dist-info/top_level.txt
sopel_stocks-2.0.2.dist-info/RECORD
